iris_vector_graph/__init__.py
iris_vector_graph/engine.py
iris_vector_graph/fusion.py
iris_vector_graph/operators.py
iris_vector_graph/py.typed
iris_vector_graph/schema.py
iris_vector_graph/text_search.py
iris_vector_graph/utils.py
iris_vector_graph/vector_utils.py
iris_vector_graph/cypher/__init__.py
iris_vector_graph/cypher/ast.py
iris_vector_graph/cypher/lexer.py
iris_vector_graph/cypher/parser.py
iris_vector_graph/cypher/translator.py
iris_vector_graph/cypher/algorithms/__init__.py
iris_vector_graph/cypher/algorithms/paths.py
iris_vector_graph/gql/__init__.py
iris_vector_graph-1.4.8.dist-info/METADATA
iris_vector_graph-1.4.8.dist-info/WHEEL
iris_vector_graph-1.4.8.dist-info/entry_points.txt
iris_vector_graph-1.4.8.dist-info/licenses/LICENSE
iris_vector_graph-1.4.8.dist-info/RECORD
