Metadata-Version: 2.4
Name: iris-vector-graph
Version: 1.4.8
Summary: Transactional Graph + Vector retrieval system for InterSystems IRIS with hybrid search, openCypher, and GraphQL APIs
Project-URL: Homepage, https://github.com/isc-tdyar/iris-vector-graph
Project-URL: Documentation, https://github.com/isc-tdyar/iris-vector-graph/tree/main/docs
Project-URL: Repository, https://github.com/isc-tdyar/iris-vector-graph
Project-URL: Issues, https://github.com/isc-tdyar/iris-vector-graph/issues
Author-email: InterSystems Community Team <grants@intersystems.com>
License-Expression: MIT
License-File: LICENSE
Keywords: bioinformatics,biomedical,graph,iris,knowledge-graph,protein-interactions,vector-search
Classifier: Development Status :: 4 - Beta
Classifier: Intended Audience :: Science/Research
Classifier: License :: OSI Approved :: MIT License
Classifier: Operating System :: OS Independent
Classifier: Programming Language :: Python :: 3
Classifier: Programming Language :: Python :: 3.9
Classifier: Programming Language :: Python :: 3.10
Classifier: Programming Language :: Python :: 3.11
Classifier: Programming Language :: Python :: 3.12
Classifier: Topic :: Database
Classifier: Topic :: Scientific/Engineering
Classifier: Topic :: Scientific/Engineering :: Bio-Informatics
Requires-Python: >=3.10
Requires-Dist: fastapi>=0.118.0
Requires-Dist: httpx>=0.28.1
Requires-Dist: intersystems-irispython>=3.2.0
Requires-Dist: networkx>=3.0
Requires-Dist: numpy>=1.24.0
Requires-Dist: pandas>=2.0.0
Requires-Dist: py2neo>=2021.2.4
Requires-Dist: pydantic>=2.11.9
Requires-Dist: pytest-asyncio>=1.2.0
Requires-Dist: python-dotenv>=1.0.0
Requires-Dist: requests>=2.28.0
Requires-Dist: strawberry-graphql[fastapi]>=0.280.0
Requires-Dist: uvicorn>=0.37.0
Provides-Extra: biodata
Requires-Dist: biopython>=1.81; extra == 'biodata'
Requires-Dist: bioservices>=1.11.0; extra == 'biodata'
Requires-Dist: mygene>=3.2.0; extra == 'biodata'
Provides-Extra: demo
Requires-Dist: python-fasthtml>=0.12.0; extra == 'demo'
Provides-Extra: dev
Requires-Dist: black>=23.0.0; extra == 'dev'
Requires-Dist: flake8>=6.0.0; extra == 'dev'
Requires-Dist: iris-devtester>=1.8.1; extra == 'dev'
Requires-Dist: isort>=5.12.0; extra == 'dev'
Requires-Dist: mypy>=1.5.0; extra == 'dev'
Requires-Dist: pytest-asyncio>=0.21.0; extra == 'dev'
Requires-Dist: pytest-playwright>=0.7.0; extra == 'dev'
Requires-Dist: pytest>=7.4.0; extra == 'dev'
Provides-Extra: ml
Requires-Dist: scikit-learn>=1.3.0; extra == 'ml'
Requires-Dist: scipy>=1.11.0; extra == 'ml'
Requires-Dist: torch>=2.0.0; extra == 'ml'
Provides-Extra: performance
Requires-Dist: memory-profiler>=0.61.0; extra == 'performance'
Requires-Dist: psutil>=5.9.0; extra == 'performance'
Provides-Extra: visualization
Requires-Dist: graphviz>=0.20.0; extra == 'visualization'
Requires-Dist: matplotlib>=3.7.0; extra == 'visualization'
Requires-Dist: plotly>=5.15.0; extra == 'visualization'
